{
    "id": "funding-pips-exclusive-audit",
    "firm_name": "Funding Pips",
    "category": "forex",
    "discount_highlight": "10% OFF",
    "coupon_code": "EXCLUSIVE_LINK",
    "theme_color": "#4DEFEF",
    "features": [
        "Institutional Stability",
        "No Time Limits",
        "Elite Execution Audit"
    ],
    "affiliate_link": "https://fundingpips.com/?ref=REELS",
    "firm_logo": "/images/logos/funding-pips.svg",
    "seo_content": "<h3>Funding Pips: The Elite Intelligence Deal</h3><p>For those who value substance over flash. Secure a verified **10% discount** on the industry's most respected stability node. A masterpiece of execution and trust.</p>",
    "created_at": "2026-02-21T09:00:00Z"
}
