{
  "id": "premiere-spotlight-funded-trading-plus-20chal-rtiyq",
  "firm_name": "Funded Trading Plus",
  "category": "forex",
  "discount_highlight": "20% OFF",
  "title": "Director's Pick: Funded Trading Plus – 20% OFF Your Masterclass Journey",
  "description": "The curtain rises on an unprecedented opportunity! Funded Trading Plus unveils a spectacular 20% discount, inviting you to star in your own trading success story.",
  "coupon_code": "20CHAL",
  "expiration_date": "2026-12-31",
  "theme_color": "#FF2D55",
  "features": [
    "Verified Deal",
    "Prop Training Excellence"
  ],
  "affiliate_link": "#",
  "seo_content": "<h3>Funded Trading Plus Promo</h3><p>Verified discount for Funded Trading Plus.</p>",
  "firm_logo": "/images/logos/funded-trading-plus.png",
  "created_at": "2026-03-14T20:57:10.225138Z"
}