{
    "id": "qt-funded-50-off-qt50",
    "canonical_slug": "qt-funded",
    "firm_name": "QT Funded",
    "category": "forex",
    "discount_highlight": "50% OFF",
    "coupon_code": "QT50",
    "theme_color": "#7C3AED",
    "features": [
        "QuantTekel Ecosystem",
        "Buy One Get One Free",
        "Instant Profit Flow"
    ],
    "affiliate_link": "https://qtfunded.quanttekel.com/ref/5288/",
    "firm_logo": "/images/logos/qt-funded.png",
    "seo_content": "<h3>QT Funded 50% OFF Deal</h3><p>QT Funded is offering an exceptional <b>50% discount</b> on QT Prime challenge accounts using code <b>QT50</b>. This promotion also includes a <b>FREE Instant account</b> of the same size as your purchased QT Prime challenge — effectively making this a buy-one-get-one deal at half price. For traders looking to maximize their funded capital exposure per dollar spent, this is one of the highest-value single promotions in the current prop trading market.</p><p>QT Funded operates within the QuantTekel ecosystem — a proprietary financial technology environment built to support serious funded traders with cutting-edge tools, robust account management, and a focus on instant profit flow. The firm has gained recognition for combining technological innovation with trader-centric promotional structures that reward committed traders with outsized value.</p><p>With code <b>QT50</b>, you purchase a QT Prime challenge at 50% of the standard price and simultaneously receive a free Instant account of matching size. This dual-account approach means you have two simultaneous paths to profitability: the challenge track, where you are working toward funded status through the evaluation, and the instant account, where you can begin trading and earning payouts immediately. The instant account profit flow begins from day one without any evaluation requirements.</p><p>QT Funded's trading conditions through the QuantTekel ecosystem include access to professional trading platforms, competitive profit splits on funded accounts, and clearly defined challenge parameters. The QT Prime challenge structure is designed for traders ready to demonstrate professional-level performance, with standard profit targets and drawdown rules. Payout processing is handled through the QuantTekel platform's integrated payment infrastructure.</p><p>To claim this BOGO deal, visit QT Funded via the affiliate link above, select the QT Prime challenge at your preferred account size, and enter <b>QT50</b> at checkout. Your 50% discount will be applied and your free Instant account of the same size will be added to your order automatically. Review the QT Prime challenge terms on the QuantTekel site to confirm the profit targets and drawdown parameters before purchasing.</p>",
    "created_at": "2026-03-02T15:46:00Z"
}